ClauseWizard/__init__.py
ClauseWizard/format.py
ClauseWizard/parse.py
sample/__init__.py
ClauseWizard-1.0.4.dist-info/LICENSE
ClauseWizard-1.0.4.dist-info/METADATA
ClauseWizard-1.0.4.dist-info/WHEEL
ClauseWizard-1.0.4.dist-info/entry_points.txt
ClauseWizard-1.0.4.dist-info/top_level.txt
ClauseWizard-1.0.4.dist-info/RECORD
